odoo/addons/easy_switch_user/README.rst
odoo/addons/easy_switch_user/__init__.py
odoo/addons/easy_switch_user/__manifest__.py
odoo/addons/easy_switch_user/controllers/__init__.py
odoo/addons/easy_switch_user/controllers/main.py
odoo/addons/easy_switch_user/static/src/js/switch_user.js
odoo/addons/easy_switch_user/static/src/xml/switch_user.xml
odoo/addons/easy_switch_user/templates/assets.xml
odoo/addons/easy_switch_user/tests/__init__.py
odoo/addons/easy_switch_user/tests/test_controller.py
odoo11_addon_easy_switch_user-11.0.1.0.0.dist-info/DESCRIPTION.rst
odoo11_addon_easy_switch_user-11.0.1.0.0.dist-info/METADATA
odoo11_addon_easy_switch_user-11.0.1.0.0.dist-info/RECORD
odoo11_addon_easy_switch_user-11.0.1.0.0.dist-info/WHEEL
odoo11_addon_easy_switch_user-11.0.1.0.0.dist-info/metadata.json
odoo11_addon_easy_switch_user-11.0.1.0.0.dist-info/top_level.txt
